pai_client/__init__.py
pai_client/pai_client.py
pai_client-0.0.5.dist-info/METADATA
pai_client-0.0.5.dist-info/WHEEL
pai_client-0.0.5.dist-info/top_level.txt
pai_client-0.0.5.dist-info/RECORD
